Metadata-Version: 2.2
Name: image_proccesing
Version: 0.0.1
Home-page: https://github.com/yDigss/image-processing-package.git
Author: Rodrigo
Requires-Python: >=3.5
Requires-Dist: matplotlib
Requires-Dist: numpy
Requires-Dist: scikit-image>=0.16.1
Dynamic: author
Dynamic: description
Dynamic: description-content-type
Dynamic: home-page
Dynamic: requires-dist
Dynamic: requires-python
